mylli/__init__.py
mylli/__main__.py
mylli/engineapi.py
mylli/mailing_list.xo
mylli/model.py
mylli-0.2.3.dist-info/DESCRIPTION.rst
mylli-0.2.3.dist-info/METADATA
mylli-0.2.3.dist-info/RECORD
mylli-0.2.3.dist-info/WHEEL
mylli-0.2.3.dist-info/entry_points.txt
mylli-0.2.3.dist-info/metadata.json
mylli-0.2.3.dist-info/top_level.txt
