Metadata-Version: 2.0
Name: mylli
Version: 0.2.3
Summary: Simple Mailing Client
Home-page: https://github.com/ignertic/mylli
Author: Gishobert (SuperCode) Gwenzi
Author-email: ilovebugsincode@gmail.com
License: MIT
Platform: UNKNOWN
Classifier: Programming Language :: Python :: 3
Classifier: Operating System :: OS Independent
Requires-Dist: loguru
Requires-Dist: requests
Requires-Dist: sendgrid
